bento/__init__.py
bento/_constants.py
bento/_utils.py
bento/datasets/__init__.py
bento/datasets/_datasets.py
bento/datasets/datasets.csv
bento/datasets/merfish_sample.h5ad
bento/datasets/seqfish_sample.h5ad
bento/datasets/bt_small_data.zarr/.zgroup
bento/datasets/bt_small_data.zarr/zmetadata
bento/datasets/bt_small_data.zarr/points/.zgroup
bento/datasets/bt_small_data.zarr/points/transcripts/.zattrs
bento/datasets/bt_small_data.zarr/points/transcripts/.zgroup
bento/datasets/bt_small_data.zarr/points/transcripts/points.parquet/part.0.parquet
bento/datasets/bt_small_data.zarr/shapes/.zgroup
bento/datasets/bt_small_data.zarr/shapes/cell_boundaries/.zattrs
bento/datasets/bt_small_data.zarr/shapes/cell_boundaries/.zgroup
bento/datasets/bt_small_data.zarr/shapes/cell_boundaries/Index/.zarray
bento/datasets/bt_small_data.zarr/shapes/cell_boundaries/Index/0
bento/datasets/bt_small_data.zarr/shapes/cell_boundaries/coords/.zarray
bento/datasets/bt_small_data.zarr/shapes/cell_boundaries/coords/0/0
bento/datasets/bt_small_data.zarr/shapes/cell_boundaries/offset0/.zarray
bento/datasets/bt_small_data.zarr/shapes/cell_boundaries/offset0/0
bento/datasets/bt_small_data.zarr/shapes/cell_boundaries/offset1/.zarray
bento/datasets/bt_small_data.zarr/shapes/cell_boundaries/offset1/0
bento/datasets/bt_small_data.zarr/shapes/cell_circles/.zattrs
bento/datasets/bt_small_data.zarr/shapes/cell_circles/.zgroup
bento/datasets/bt_small_data.zarr/shapes/cell_circles/Index/.zarray
bento/datasets/bt_small_data.zarr/shapes/cell_circles/Index/0
bento/datasets/bt_small_data.zarr/shapes/cell_circles/coords/.zarray
bento/datasets/bt_small_data.zarr/shapes/cell_circles/coords/0/0
bento/datasets/bt_small_data.zarr/shapes/cell_circles/radius/.zarray
bento/datasets/bt_small_data.zarr/shapes/cell_circles/radius/0
bento/datasets/bt_small_data.zarr/shapes/nucleus_boundaries/.zattrs
bento/datasets/bt_small_data.zarr/shapes/nucleus_boundaries/.zgroup
bento_tools-2.1.4.post2.dist-info/METADATA
bento_tools-2.1.4.post2.dist-info/WHEEL
bento_tools-2.1.4.post2.dist-info/licenses/LICENSE
bento_tools-2.1.4.post2.dist-info/RECORD
